setup.py
hello_roy/__init__ .py
hello_roy/operation.py
hello_roy.egg-info/PKG-INFO
hello_roy.egg-info/SOURCES.txt
hello_roy.egg-info/dependency_links.txt
hello_roy.egg-info/not-zip-safe
hello_roy.egg-info/top_level.txt