Metadata-Version: 2.1
Name: hello_roy
Version: 0.1
Summary: To greet everyone using Hello
Author-email: nilabjaroy5@gmail.com
